{"playerId":8484494,"isActive":true,"currentTeamId":18,"currentTeamAbbrev":"NSH","fullTeamName":{"default":"Nashville Predators","fr":"Predators de Nashville"},"teamCommonName":{"default":"Predators"},"teamPlaceNameWithPreposition":{"default":"Nashville","fr":"de Nashville"},"firstName":{"default":"Aiden"},"lastName":{"default":"Fink"},"badges":[],"teamLogo":"https://assets.nhle.com/logos/nhl/svg/NSH_light.svg","sweaterNumber":18,"position":"R","headshot":"https://assets.nhle.com/mugs/nhl/20252026/NSH/8484494.png","heroImage":"https://assets.nhle.com/mugs/actionshots/1296x729/8484494.jpg","heightInInches":70,"heightInCentimeters":178,"weightInPounds":164,"weightInKilograms":74,"birthDate":"2004-11-24","birthCity":{"default":"Calgary"},"birthStateProvince":{"default":"Alberta"},"birthCountry":"CAN","shootsCatches":"R","draftDetails":{"year":2023,"teamAbbrev":"NSH","round":7,"pickInRound":26,"overallPick":218},"playerSlug":"aiden-fink-8484494","inTop100AllTime":0,"inHHOF":0,"shopLink":"#TODO","twitterLink":"#TODO","watchLink":"#TODO","seasonTotals":[{"assists":18,"gameTypeId":2,"gamesPlayed":30,"goals":10,"leagueAbbrev":"HCBAA","pim":24,"points":28,"season":20172018,"sequence":11,"teamName":{"default":"NWCAA Stamps U15 AA"}},{"assists":18,"gameTypeId":2,"gamesPlayed":33,"goals":13,"leagueAbbrev":"AMBHL","pim":6,"points":31,"season":20182019,"sequence":11,"teamName":{"default":"Calgary Flames U15 AAA"}},{"assists":3,"gameTypeId":2,"gamesPlayed":5,"goals":1,"leagueAbbrev":"Alberta Cup","pim":0,"points":4,"season":20182019,"sequence":11,"teamName":{"default":"Team Alberta Red"}},{"assists":1,"gameTypeId":3,"gamesPlayed":5,"goals":2,"leagueAbbrev":"AMBHL","pim":0,"points":3,"season":20182019,"sequence":11,"teamName":{"default":"Calgary Flames U15 AAA"}},{"assists":28,"gameTypeId":2,"gamesPlayed":27,"goals":16,"leagueAbbrev":"CSSHL U16","pim":10,"points":44,"season":20192020,"sequence":11,"teamName":{"default":"Northern Alberta Xtreme U16 Prep"}},{"assists":2,"gameTypeId":2,"gamesPlayed":1,"goals":0,"leagueAbbrev":"CSSHL U18","pim":2,"points":2,"season":20192020,"sequence":12,"teamName":{"default":"Northern Alberta Xtreme U18 Prep"}},{"assists":1,"gameTypeId":3,"gamesPlayed":2,"goals":0,"leagueAbbrev":"CSSHL U16","pim":0,"points":1,"season":20192020,"sequence":11,"teamName":{"default":"Northern Alberta Xtreme U16 Prep"}},{"assists":2,"gameTypeId":2,"gamesPlayed":3,"goals":1,"leagueAbbrev":"CSSHL U18","pim":2,"points":3,"season":20202021,"sequence":11,"teamName":{"default":"Northern Alberta Xtreme U18 Prep"}},{"assists":34,"gameTypeId":2,"gamesPlayed":60,"goals":19,"leagueAbbrev":"AJHL","pim":36,"points":53,"season":20212022,"sequence":11,"teamName":{"default":"Brooks Bandits"}},{"assists":4,"gameTypeId":3,"gamesPlayed":13,"goals":6,"leagueAbbrev":"AJHL","pim":2,"points":10,"season":20212022,"sequence":11,"teamName":{"default":"Brooks Bandits"}},{"assists":56,"gameTypeId":2,"gamesPlayed":54,"goals":41,"leagueAbbrev":"AJHL","pim":32,"points":97,"season":20222023,"sequence":11,"teamName":{"default":"Brooks Bandits"}},{"assists":7,"gameTypeId":2,"gamesPlayed":6,"goals":5,"leagueAbbrev":"WJAC-19","pim":2,"points":12,"season":20222023,"sequence":12,"teamName":{"default":"Canada West U19"}},{"assists":5,"gameTypeId":3,"gamesPlayed":15,"goals":8,"leagueAbbrev":"AJHL","pim":0,"points":13,"season":20222023,"sequence":11,"teamName":{"default":"Brooks Bandits"}},{"assists":19,"gameTypeId":2,"gamesPlayed":34,"goals":15,"leagueAbbrev":"NCAA","pim":27,"plusMinus":-3,"points":34,"season":20232024,"sequence":11,"teamName":{"default":"Penn State Univ."}},{"assists":30,"gameTypeId":2,"gamesPlayed":40,"goals":23,"leagueAbbrev":"NCAA","pim":12,"plusMinus":15,"points":53,"season":20242025,"sequence":11,"teamName":{"default":"Penn State Univ."}},{"assists":28,"gameTypeId":2,"gamesPlayed":30,"goals":10,"leagueAbbrev":"NCAA","pim":20,"plusMinus":-4,"points":38,"season":20252026,"sequence":11,"teamName":{"default":"Penn State Univ."}},{"assists":7,"gameTypeId":2,"gamesPlayed":6,"goals":3,"leagueAbbrev":"AHL","pim":0,"plusMinus":2,"points":10,"season":20252026,"sequence":12,"teamName":{"default":"Milwaukee Admirals"}}],"currentTeamRoster":[{"playerId":8481020,"lastName":{"default":"Annunen"},"firstName":{"default":"Justus"},"playerSlug":"justus-annunen-8481020"},{"playerId":8482111,"lastName":{"default":"Barron"},"firstName":{"default":"Justin"},"playerSlug":"justin-barron-8482111"},{"playerId":8482146,"lastName":{"default":"Evangelista"},"firstName":{"default":"Luke"},"playerSlug":"luke-evangelista-8482146"},{"playerId":8484494,"lastName":{"default":"Fink"},"firstName":{"default":"Aiden"},"playerSlug":"aiden-fink-8484494"},{"playerId":8476887,"lastName":{"default":"Forsberg"},"firstName":{"default":"Filip"},"playerSlug":"filip-forsberg-8476887"},{"playerId":8479980,"lastName":{"default":"Hague"},"firstName":{"default":"Nicolas"},"playerSlug":"nicolas-hague-8479980"},{"playerId":8475287,"lastName":{"default":"Haula"},"firstName":{"default":"Erik"},"playerSlug":"erik-haula-8475287"},{"playerId":8474600,"lastName":{"default":"Josi"},"firstName":{"default":"Roman"},"playerSlug":"roman-josi-8474600"},{"playerId":8479370,"lastName":{"default":"Jost"},"firstName":{"default":"Tyson"},"playerSlug":"tyson-jost-8479370"},{"playerId":8476539,"lastName":{"default":"Marchessault"},"firstName":{"default":"Jonathan"},"playerSlug":"jonathan-marchessault-8476539"},{"playerId":8475158,"lastName":{"default":"O'Reilly"},"firstName":{"default":"Ryan"},"playerSlug":"ryan-o-reilly-8475158"},{"playerId":8480246,"lastName":{"default":"Perbix"},"firstName":{"default":"Nick","cs":"Nicklaus","de":"Nicklaus","es":"Nicklaus","fi":"Nicklaus","sk":"Nicklaus","sv":"Nicklaus"},"playerSlug":"nick-perbix-8480246"},{"playerId":8477424,"lastName":{"default":"Saros"},"firstName":{"default":"Juuse"},"playerSlug":"juuse-saros-8477424"},{"playerId":8476869,"lastName":{"default":"Skjei"},"firstName":{"default":"Brady"},"playerSlug":"brady-skjei-8476869"},{"playerId":8474564,"lastName":{"default":"Stamkos"},"firstName":{"default":"Steven"},"playerSlug":"steven-stamkos-8474564"},{"playerId":8482768,"lastName":{"default":"Svechkov"},"firstName":{"default":"Fedor"},"playerSlug":"fedor-svechkov-8482768"},{"playerId":8482103,"lastName":{"default":"Wiesblatt"},"firstName":{"default":"Ozzy"},"playerSlug":"ozzy-wiesblatt-8482103"},{"playerId":8482482,"lastName":{"default":"Wilsby"},"firstName":{"default":"Adam"},"playerSlug":"adam-wilsby-8482482"},{"playerId":8484241,"lastName":{"default":"Wood"},"firstName":{"default":"Matthew"},"playerSlug":"matthew-wood-8484241"}]}